<?xml version="1.0"?>
<fr:recipe xmlns:fr="http://fruschtique.de/ns/recipe" xmlns:xsi="http://www.w3.org/2001/XMLSchema-instance" xsi:schemaLocation="http://fruschtique.de/ns/recipe file:///c:/Users/nlutt/Documents/Websites/tools/recipe.xsd" rcpID="recipe-399661128873243">
  <fr:meta>
    <fr:book>ckCollections</fr:book>
    <fr:chapter>03 Mangold</fr:chapter>
  </fr:meta>
  <fr:recipeName>recipe-399661128873243 - Arabisches Mangodessert</fr:recipeName>
  <fr:recipeKeywords/>
  <fr:recipeIntro/>
  <fr:recipeIngredients>
    <fr:igdtList>
      <fr:igdtListName/>
      <fr:igdtListLine>
        <fr:igdtQuantity>1 Dose/n</fr:igdtQuantity>
        <fr:igdtName>Mango(s), in Spalten (425 g EW) oder Fruchtfleisch von 2 reifen Mangos</fr:igdtName>
      </fr:igdtListLine>
      <fr:igdtListLine>
        <fr:igdtQuantity>600 g</fr:igdtQuantity>
        <fr:igdtName>Joghurt (Vollmilch-)</fr:igdtName>
      </fr:igdtListLine>
      <fr:igdtListLine>
        <fr:igdtQuantity>2 EL</fr:igdtQuantity>
        <fr:igdtName>Zitronensaft</fr:igdtName>
      </fr:igdtListLine>
      <fr:igdtListLine>
        <fr:igdtQuantity>1 EL</fr:igdtQuantity>
        <fr:igdtName>Honig, flüssiger</fr:igdtName>
      </fr:igdtListLine>
      <fr:igdtListLine>
        <fr:igdtQuantity>1</fr:igdtQuantity>
        <fr:igdtName>Vanilleschote(n) (Mark ) oder Vanille-Essenz</fr:igdtName>
      </fr:igdtListLine>
      <fr:igdtListLine>
        <fr:igdtQuantity>2 Msp.</fr:igdtQuantity>
        <fr:igdtName>Safranfäden</fr:igdtName>
      </fr:igdtListLine>
      <fr:igdtListLine>
        <fr:igdtQuantity>1</fr:igdtQuantity>
        <fr:igdtName>Mango(s), reif</fr:igdtName>
      </fr:igdtListLine>
      <fr:igdtListLine>
        <fr:igdtQuantity>20 g</fr:igdtQuantity>
        <fr:igdtName>Pistazien</fr:igdtName>
      </fr:igdtListLine>
    </fr:igdtList>
  </fr:recipeIngredients>
  <fr:recipeInstructions>
    <fr:instruction>
      <fr:instrStepName/>
      <fr:instrStepText/>
    </fr:instruction>
  </fr:recipeInstructions>
  <fr:recipeSideDish/>
  <fr:recipeOrigin/>
  <fr:recipeSeeAlso/>
  <fr:recipeLicense/>
</fr:recipe>