<fr:recipe xmlns:fr="http://fruschtique.de/ns/recipe" xmlns:xsi="http://www.w3.org/2001/XMLSchema-instance" xsi:schemaLocation="http://fruschtique.de/ns/recipe file:///c:/Users/nlutt/Documents/Websites/tools/recipe.xsd" rcpID="ck-2c42bbd0-1a96-4eff-a98f-baf8605ebdaf">
  <fr:meta>
    <fr:book />
    <fr:chapter />
  </fr:meta>
  <fr:recipeName>Bl&#228;tterteig-Quiche mit Brokkoli und Camembert</fr:recipeName>
  <fr:recipeKeywords />
  <fr:recipeIntro />
  <fr:recipeIngredients>
    <fr:igdtList>
      <fr:igdtListName />
      <fr:igdtListLine>
        <fr:igdtQuantity>1 Pck.</fr:igdtQuantity>
        <fr:igdtName ref="bl&#228;tterteig">Bl&#228;tterteig aus dem K&#252;hlregal</fr:igdtName>
      </fr:igdtListLine>
      <fr:igdtListLine>
        <fr:igdtQuantity>600 g</fr:igdtQuantity>
        <fr:igdtName ref="blumenkohl">Brokkoli oder Blumenkohl, Mangold oder Spinat</fr:igdtName>
      </fr:igdtListLine>
      <fr:igdtListLine>
        <fr:igdtQuantity>200 g</fr:igdtQuantity>
        <fr:igdtName ref="camembert">Camembert(s)</fr:igdtName>
      </fr:igdtListLine>
      <fr:igdtListLine>
        <fr:igdtQuantity>200 ml</fr:igdtQuantity>
        <fr:igdtName ref="sahne">Sahne</fr:igdtName>
      </fr:igdtListLine>
      <fr:igdtListLine>
        <fr:igdtQuantity>1 Prise(n)</fr:igdtQuantity>
        <fr:igdtName ref="muskat">Muskat</fr:igdtName>
      </fr:igdtListLine>
      <fr:igdtListLine>
        <fr:igdtQuantity>2</fr:igdtQuantity>
        <fr:igdtName ref="ei">Ei(er)</fr:igdtName>
      </fr:igdtListLine>
      <fr:igdtListLine>
        <fr:igdtQuantity />
        <fr:igdtName ref="pfeffer">Salz und Pfeffer</fr:igdtName>
      </fr:igdtListLine>
    </fr:igdtList>
  </fr:recipeIngredients>
  <fr:recipeInstructions>
    <fr:instruction>
      <fr:instrStepName />
      <fr:instrStepText>Den Bl&#228;tterteig in einer Springform auslegen. Den Backofen auf 180&#176;C Umluft vorheizen. Den Brokkoli waschen und in kleine R&#246;schen zerteilen.
In einem Topf etwas Wasser aufsetzen, den Brokkoli hineingeben und ca. 5 Minuten bei mittlerer Hitze garen. In einem Sieb abgie&#223;en, abtropfen lassen und auf den Teig verteilen. Den K&#228;se in d&#252;nne Scheiben schneiden und dekorativ auf den Brokkoli legen.
Die Sahne mit Eiern und Gew&#252;rzen verquirlen und &#252;ber den Brokkoli und K&#228;se gie&#223;en. Dann auf der mittleren Schiene etwa 40 - 45 Minuten goldgelb backen.
Wer mag, kann den Brokkoli auch durch anderes Gem&#252;se (z. B. frischen Blattspinat - dann aber 1 kg, Mangold oder Blumenkohl) ersetzen. Wer keinen Camembert mag, kann auch Feta-K&#228;se nehmen, dann bekommt die Quiche eine ganz andere Note und das Gericht ist trotzdem stark basisch. Dazu passt noch ein basischer Salat mit Zitronendressing.</fr:instrStepText>
    </fr:instruction>
  </fr:recipeInstructions>
  <fr:recipeSideDish />
  <fr:recipeOrigin />
  <fr:recipeSeeAlso />
  <fr:recipeLicense />
</fr:recipe>