<?xml version="1.0"?>
<fr:recipe xmlns:fr="http://fruschtique.de/ns/recipe" xmlns:xsi="http://www.w3.org/2001/XMLSchema-instance" xsi:schemaLocation="http://fruschtique.de/ns/recipe file:///c:/Users/nlutt/Documents/Websites/tools/recipe.xsd" rcpID="recipe-2296981366202760">
  <fr:meta>
    <fr:book>ckCollections</fr:book>
    <fr:chapter>03 Mangold</fr:chapter>
  </fr:meta>
  <fr:recipeName>recipe-2296981366202760 - Ingis fluffiger Dinkel-Ahornsirup-Apfelkuchen</fr:recipeName>
  <fr:recipeKeywords/>
  <fr:recipeIntro/>
  <fr:recipeIngredients>
    <fr:igdtList>
      <fr:igdtListName/>
      <fr:igdtListLine>
        <fr:igdtQuantity>6</fr:igdtQuantity>
        <fr:igdtName>Äpfel, säuerliche (z. B. Maigold)</fr:igdtName>
      </fr:igdtListLine>
      <fr:igdtListLine>
        <fr:igdtQuantity>6</fr:igdtQuantity>
        <fr:igdtName>Ei(er)</fr:igdtName>
      </fr:igdtListLine>
      <fr:igdtListLine>
        <fr:igdtQuantity>300 g</fr:igdtQuantity>
        <fr:igdtName>Butter</fr:igdtName>
      </fr:igdtListLine>
      <fr:igdtListLine>
        <fr:igdtQuantity>180 g</fr:igdtQuantity>
        <fr:igdtName>Ahornsirup</fr:igdtName>
      </fr:igdtListLine>
      <fr:igdtListLine>
        <fr:igdtQuantity>180 g</fr:igdtQuantity>
        <fr:igdtName>Fruchtzucker</fr:igdtName>
      </fr:igdtListLine>
      <fr:igdtListLine>
        <fr:igdtQuantity>250 g</fr:igdtQuantity>
        <fr:igdtName>Dinkelmehl, Vollkorn</fr:igdtName>
      </fr:igdtListLine>
      <fr:igdtListLine>
        <fr:igdtQuantity>250 g</fr:igdtQuantity>
        <fr:igdtName>Dinkelmehl (Type 630)</fr:igdtName>
      </fr:igdtListLine>
      <fr:igdtListLine>
        <fr:igdtQuantity>2 Pck.</fr:igdtQuantity>
        <fr:igdtName>Vanillezucker</fr:igdtName>
      </fr:igdtListLine>
      <fr:igdtListLine>
        <fr:igdtQuantity>½ TL</fr:igdtQuantity>
        <fr:igdtName>Zimtpulver, nach Geschmack, evtl.</fr:igdtName>
      </fr:igdtListLine>
      <fr:igdtListLine>
        <fr:igdtQuantity>½ TL</fr:igdtQuantity>
        <fr:igdtName>Salz</fr:igdtName>
      </fr:igdtListLine>
      <fr:igdtListLine>
        <fr:igdtQuantity>1 Pck.</fr:igdtQuantity>
        <fr:igdtName>Backpulver</fr:igdtName>
      </fr:igdtListLine>
      <fr:igdtListLine>
        <fr:igdtQuantity>1</fr:igdtQuantity>
        <fr:igdtName>Zitrone(n), den Saft davon oder 100 m Zitronensaft</fr:igdtName>
      </fr:igdtListLine>
      <fr:igdtListLine>
        <fr:igdtQuantity>1 EL</fr:igdtQuantity>
        <fr:igdtName>Margarine für die Form</fr:igdtName>
      </fr:igdtListLine>
      <fr:igdtListLine>
        <fr:igdtQuantity>2 EL</fr:igdtQuantity>
        <fr:igdtName>Paniermehl für die Form</fr:igdtName>
      </fr:igdtListLine>
      <fr:igdtListLine>
        <fr:igdtQuantity>2 EL</fr:igdtQuantity>
        <fr:igdtName>Süßstoff (Streusüße) oder Puderzucker zum Bestäuben</fr:igdtName>
      </fr:igdtListLine>
    </fr:igdtList>
  </fr:recipeIngredients>
  <fr:recipeInstructions>
    <fr:instruction>
      <fr:instrStepName/>
      <fr:instrStepText/>
    </fr:instruction>
  </fr:recipeInstructions>
  <fr:recipeSideDish/>
  <fr:recipeOrigin/>
  <fr:recipeSeeAlso/>
  <fr:recipeLicense/>
</fr:recipe>