<fr:recipe xmlns:fr="http://fruschtique.de/ns/recipe" xmlns:xsi="http://www.w3.org/2001/XMLSchema-instance" xsi:schemaLocation="http://fruschtique.de/ns/recipe file:///c:/Users/nlutt/Documents/Websites/tools/recipe.xsd" rcpID="ck-a418e374-5b28-4920-aa46-3aaf12fc8805">
  <fr:meta>
    <fr:book />
    <fr:chapter />
  </fr:meta>
  <fr:recipeName>Mangoldsalat italienisch</fr:recipeName>
  <fr:recipeKeywords />
  <fr:recipeIntro />
  <fr:recipeIngredients>
    <fr:igdtList>
      <fr:igdtListName />
      <fr:igdtListLine>
        <fr:igdtQuantity>200 g</fr:igdtQuantity>
        <fr:igdtName ref="mangold">Mangold</fr:igdtName>
      </fr:igdtListLine>
      <fr:igdtListLine>
        <fr:igdtQuantity>150 g</fr:igdtQuantity>
        <fr:igdtName ref="paprika">Paprikaschote(n), gr&#252;n</fr:igdtName>
      </fr:igdtListLine>
      <fr:igdtListLine>
        <fr:igdtQuantity>100 g</fr:igdtQuantity>
        <fr:igdtName ref="lauch">Lauch</fr:igdtName>
      </fr:igdtListLine>
      <fr:igdtListLine>
        <fr:igdtQuantity>2 EL</fr:igdtQuantity>
        <fr:igdtName ref="oliven&#246;l">Oliven&#246;l</fr:igdtName>
      </fr:igdtListLine>
      <fr:igdtListLine>
        <fr:igdtQuantity>1</fr:igdtQuantity>
        <fr:igdtName ref="knoblauch">Knoblauchzehe(n)</fr:igdtName>
      </fr:igdtListLine>
      <fr:igdtListLine>
        <fr:igdtQuantity>2 Bl&#228;tter</fr:igdtQuantity>
        <fr:igdtName ref="liebst&#246;ckel">Liebst&#246;ckel</fr:igdtName>
      </fr:igdtListLine>
      <fr:igdtListLine>
        <fr:igdtQuantity>8</fr:igdtQuantity>
        <fr:igdtName ref="rosmarin">Rosmarin, frisch gehackt</fr:igdtName>
      </fr:igdtListLine>
      <fr:igdtListLine>
        <fr:igdtQuantity>2 TL</fr:igdtQuantity>
        <fr:igdtName ref="thymian">Thymian</fr:igdtName>
      </fr:igdtListLine>
      <fr:igdtListLine>
        <fr:igdtQuantity />
        <fr:igdtName ref="">Salz</fr:igdtName>
      </fr:igdtListLine>
      <fr:igdtListLine>
        <fr:igdtQuantity>100 g</fr:igdtQuantity>
        <fr:igdtName ref="tomate">Tomate(n)</fr:igdtName>
      </fr:igdtListLine>
      <fr:igdtListLine>
        <fr:igdtQuantity>3 EL</fr:igdtQuantity>
        <fr:igdtName ref="sahne">saure Sahne</fr:igdtName>
      </fr:igdtListLine>
      <fr:igdtListLine>
        <fr:igdtQuantity>1 &#189; EL</fr:igdtQuantity>
        <fr:igdtName ref="petersilie">Petersilie, frisch gehackt</fr:igdtName>
      </fr:igdtListLine>
    </fr:igdtList>
  </fr:recipeIngredients>
  <fr:recipeInstructions>
    <fr:instruction>
      <fr:instrStepName />
      <fr:instrStepText>Die Mangoldstiele und die dicken Rippen von den Bl&#228;ttern trennen, waschen und beides getrennt in 1,5 cm breite Streifen schneiden. Die Paprikaschoten vierteln, entkernen und quer in Streifen schneiden. Den Lauch putzen, waschen und in schmale Streifen schneiden.
Das &#214;l und 1 EL Wasser in einer Pfanne erhitzen. Das Gem&#252;se (auch die Mangoldstiele) bis auf die Mangoldbl&#228;tter, den durchgepressten Knoblauch und die Kr&#228;uter zugeben. Leicht salzen und 5 - 8 Minuten bei schwacher Hitze kochen. Dann die Mangoldbl&#228;tter hinein geben und vermischen. Die Tomaten putzen und grob w&#252;rfeln. Dann mit dem Gem&#252;se noch ca. 3 Minuten ziehen lassen. Die saure Sahne unterr&#252;hren. Das Gem&#252;se abschmecken und mit der Petersilie bestreuen.
Der Salat kann lauwarm oder kalt gegessen werden.</fr:instrStepText>
    </fr:instruction>
  </fr:recipeInstructions>
  <fr:recipeSideDish />
  <fr:recipeOrigin />
  <fr:recipeSeeAlso />
  <fr:recipeLicense />
</fr:recipe>