<fr:recipe xmlns:fr="http://fruschtique.de/ns/recipe" xmlns:xsi="http://www.w3.org/2001/XMLSchema-instance" xsi:schemaLocation="http://fruschtique.de/ns/recipe file:///c:/Users/nlutt/Documents/Websites/tools/recipe.xsd" rcpID="ck-18f2b9cf-2d19-4bf5-8166-e0c41e0c6914">
  <fr:meta>
    <fr:book />
    <fr:chapter />
  </fr:meta>
  <fr:recipeName>Spinatstrudel mit Feta und Tzatziki</fr:recipeName>
  <fr:recipeKeywords />
  <fr:recipeIntro />
  <fr:recipeIngredients>
    <fr:igdtList>
      <fr:igdtListName />
      <fr:igdtListLine>
        <fr:igdtQuantity>1 kg</fr:igdtQuantity>
        <fr:igdtName ref="spinat">Blattspinat</fr:igdtName>
      </fr:igdtListLine>
      <fr:igdtListLine>
        <fr:igdtQuantity>500 g</fr:igdtQuantity>
        <fr:igdtName ref="mangold">Mangold</fr:igdtName>
      </fr:igdtListLine>
      <fr:igdtListLine>
        <fr:igdtQuantity />
        <fr:igdtName ref="">Salz</fr:igdtName>
      </fr:igdtListLine>
      <fr:igdtListLine>
        <fr:igdtQuantity>20 g</fr:igdtQuantity>
        <fr:igdtName ref="petersilie">Petersilie, glatte</fr:igdtName>
      </fr:igdtListLine>
      <fr:igdtListLine>
        <fr:igdtQuantity>10 g</fr:igdtQuantity>
        <fr:igdtName ref="minze">Minze</fr:igdtName>
      </fr:igdtListLine>
      <fr:igdtListLine>
        <fr:igdtQuantity>300 g</fr:igdtQuantity>
        <fr:igdtName ref="schafsk&#228;se">Feta-K&#228;se</fr:igdtName>
      </fr:igdtListLine>
      <fr:igdtListLine>
        <fr:igdtQuantity>2</fr:igdtQuantity>
        <fr:igdtName ref="ei">Eigelb, Gr&#246;&#223;e M</fr:igdtName>
      </fr:igdtListLine>
      <fr:igdtListLine>
        <fr:igdtQuantity>1 TL</fr:igdtQuantity>
        <fr:igdtName ref="paprikapulver">Paprikapulver, edels&#252;&#223;es</fr:igdtName>
      </fr:igdtListLine>
      <fr:igdtListLine>
        <fr:igdtQuantity>&#189; TL</fr:igdtQuantity>
        <fr:igdtName ref="paprikapulver">Paprikapulver, rosenscharfes</fr:igdtName>
      </fr:igdtListLine>
      <fr:igdtListLine>
        <fr:igdtQuantity>1 TL</fr:igdtQuantity>
        <fr:igdtName ref="koriander">Koriandersamen, im M&#246;rser fein zermahlen</fr:igdtName>
      </fr:igdtListLine>
      <fr:igdtListLine>
        <fr:igdtQuantity />
        <fr:igdtName ref="pfeffer">Pfeffer</fr:igdtName>
      </fr:igdtListLine>
      <fr:igdtListLine>
        <fr:igdtQuantity>60 g</fr:igdtQuantity>
        <fr:igdtName ref="butter">Butter</fr:igdtName>
      </fr:igdtListLine>
      <fr:igdtListLine>
        <fr:igdtQuantity>10 Bl&#228;tter</fr:igdtQuantity>
        <fr:igdtName ref="teigbl&#228;tter">Filoteig</fr:igdtName>
      </fr:igdtListLine>
      <fr:igdtListLine>
        <fr:igdtQuantity>1 TL</fr:igdtQuantity>
        <fr:igdtName ref="chiliflocken">Pul Biber, ersatzweise Chiliflocken</fr:igdtName>
      </fr:igdtListLine>
      <fr:igdtListLine>
        <fr:igdtQuantity>1 EL</fr:igdtQuantity>
        <fr:igdtName ref="paniermehl">Semmelbr&#246;sel</fr:igdtName>
      </fr:igdtListLine>
      <fr:igdtListLine>
        <fr:igdtQuantity>1 TL</fr:igdtQuantity>
        <fr:igdtName ref="schwarzk&#252;mmel">Schwarzk&#252;mmelsamen</fr:igdtName>
      </fr:igdtListLine>
      <fr:igdtListLine>
        <fr:igdtQuantity>2</fr:igdtQuantity>
        <fr:igdtName ref="gurke">Salatgurke(n)</fr:igdtName>
      </fr:igdtListLine>
      <fr:igdtListLine>
        <fr:igdtQuantity />
        <fr:igdtName ref="zucker">Zucker</fr:igdtName>
      </fr:igdtListLine>
      <fr:igdtListLine>
        <fr:igdtQuantity>150 g</fr:igdtQuantity>
        <fr:igdtName ref="joghurt">Joghurt, griechischer, 10 % Fett</fr:igdtName>
      </fr:igdtListLine>
    </fr:igdtList>
  </fr:recipeIngredients>
  <fr:recipeInstructions>
    <fr:instruction>
      <fr:instrStepName />
      <fr:instrStepText>1. Spinat putzen, waschen und abtropfen lassen. Mangold putzen, waschen und die Bl&#228;tter von den Stielen trennen. Von den Bl&#228;ttern die Mittelrippe entfernen. Mangoldstiele in kleine W&#252;rfel schneiden und in kochendem Salzwasser 1&#8239;Minute garen. Stiele in ein Sieb gie&#223;en, abschrecken und gut abtropfen lassen. Mangoldbl&#228;tter in grobe St&#252;cken schneiden und mit dem Spinat in kochendem Salzwasser 30&#8239;Sekunden blanchieren. Beides in ein Sieb gie&#223;en, abschrecken und gut abtropfen lassen. Spinat-Mangold-Gem&#252;se gut ausdr&#252;cken und mittelfein hacken.
2. Petersilien- und Minzbl&#228;tter von den Stielen abzupfen und fein schneiden. Feta zerbr&#246;seln. Spinat-Mangold-Gem&#252;se in einer Sch&#252;ssel mit Petersilie, Minze, K&#228;se und Eigelb mischen, leicht mit Salz, beiden Paprikapulvern, Koriander und Pfeffer w&#252;rzen.
3. Butter in einem Topf zerlassen. Teigbl&#228;tter jeweils mit etwas fl&#252;ssiger Butter bepinseln und je 5 Bl&#228;tter &#252;bereinanderschichten, sodass 2 Stapel mit je 5 Lagen entstehen. Beide Stapel der L&#228;nge nach leicht &#252;berlappend nebeneinanderlegen und andr&#252;cken. Oberfl&#228;che mit Pulbiber und Semmelbr&#246;seln bestreuen. Spinat-K&#228;se-Mischung auf der unteren L&#228;ngsseite des Teigs verteilen, dabei einen schmalen Rand lassen. F&#252;llung fest zusammendr&#252;cken. Untere L&#228;ngsseite &#252;ber die F&#252;llung klappen, fest zusammendr&#252;cken und den Teig mit der F&#252;llung zum Strudel aufrollen. Au&#223;enseiten einklappen. Strudel diagonal auf ein mit Backpapier belegtes Backblech legen, mit restlicher Butter bepinseln und mit der Schwarzk&#252;mmelsaat bestreuen. Im vorgeheizten Backofen bei 180&#8239;Grad (Gas&#8239;2 - 3, Umluft 170&#8239;Grad) auf der 2.&#8239;Schiene von unten 35 - 40&#8239;Minuten backen.
4. Inzwischen f&#252;r das Tzatziki Gurken sch&#228;len, grob raspeln, in einem Sieb mit Salz und 1 Prise Zucker mischen und 10&#8239;Minuten ziehen lassen. Gut abtropfen lassen und in einer Sch&#252;ssel mit dem Joghurt verr&#252;hren. Mit Salz und Pfeffer w&#252;rzen.
5.&#8239;Strudel aus dem Backofen nehmen, leicht abk&#252;hlen lassen und in St&#252;cke teilen. Tzatziki separat dazu servieren.
Pro Portion 29 g E, 43 g F, 47 g KH = 723 kcal (3030 kJ)</fr:instrStepText>
    </fr:instruction>
  </fr:recipeInstructions>
  <fr:recipeSideDish />
  <fr:recipeOrigin />
  <fr:recipeSeeAlso />
  <fr:recipeLicense />
</fr:recipe>