<?xml version="1.0" ?><fr:recipe xmlns:fr="http://fruschtique.de/ns/recipe" xmlns:xsi="http://www.w3.org/2001/XMLSchema-instance" xsi:schemaLocation="http://fruschtique.de/ns/recipe file:///c:/Users/nlutt/Documents/Websites/tools/recipe.xsd" rcpID="recipe-4009311615803266">
  <fr:meta>
    <fr:book>ckCollections</fr:book>
    <fr:chapter>03 Mangold</fr:chapter>
  </fr:meta>
  <fr:recipeName>Thailändischer Kohlsalat mit Radieschen und Erdnüssen</fr:recipeName>
  <fr:recipeKeywords/>
  <fr:recipeIntro/>
  <fr:recipeIngredients>
    <fr:igdtList>
      <fr:igdtListName/>
      <fr:igdtListLine>
        <fr:igdtQuantity>½ m.-große</fr:igdtQuantity>
        <fr:igdtName ref="zwiebel">Zwiebel(n)</fr:igdtName>
      </fr:igdtListLine>
      <fr:igdtListLine>
        <fr:igdtQuantity>1 TL</fr:igdtQuantity>
        <fr:igdtName ref="">Salz</fr:igdtName>
      </fr:igdtListLine>
      <fr:igdtListLine>
        <fr:igdtQuantity>100 g</fr:igdtQuantity>
        <fr:igdtName ref="weißkohl">Weißkohl</fr:igdtName>
      </fr:igdtListLine>
      <fr:igdtListLine>
        <fr:igdtQuantity>2 kleine</fr:igdtQuantity>
        <fr:igdtName ref="brokkoli">Kailan (Chinesischer Brokkoli), ersatzweise Mangold</fr:igdtName>
      </fr:igdtListLine>
      <fr:igdtListLine>
        <fr:igdtQuantity>3 m.-große</fr:igdtQuantity>
        <fr:igdtName ref="radieschen">Radieschen</fr:igdtName>
      </fr:igdtListLine>
      <fr:igdtListLine>
        <fr:igdtQuantity>1 kleine</fr:igdtQuantity>
        <fr:igdtName ref="chilischote">Chilischote(n), grün</fr:igdtName>
      </fr:igdtListLine>
      <fr:igdtListLine>
        <fr:igdtQuantity>2 m.-große</fr:igdtQuantity>
        <fr:igdtName ref="knoblauch">Knoblauchzehe(n)</fr:igdtName>
      </fr:igdtListLine>
      <fr:igdtListLine>
        <fr:igdtQuantity>2 EL</fr:igdtQuantity>
        <fr:igdtName ref="sonnenblumenöl">Sonnenblumenöl</fr:igdtName>
      </fr:igdtListLine>
      <fr:igdtListLine>
        <fr:igdtQuantity>1</fr:igdtQuantity>
        <fr:igdtName ref="peperoni">Peperoni, rote, lang, mittelscharf</fr:igdtName>
      </fr:igdtListLine>
      <fr:igdtListLine>
        <fr:igdtQuantity>1</fr:igdtQuantity>
        <fr:igdtName ref="limette">Limone(n)</fr:igdtName>
      </fr:igdtListLine>
      <fr:igdtListLine>
        <fr:igdtQuantity>2 TL</fr:igdtQuantity>
        <fr:igdtName ref="zucker">Zucker, grobe Körnung</fr:igdtName>
      </fr:igdtListLine>
      <fr:igdtListLine>
        <fr:igdtQuantity>30 g</fr:igdtQuantity>
        <fr:igdtName ref="erdnuss">Erdnüsse, ungesalzen, geröstet</fr:igdtName>
      </fr:igdtListLine>
      <fr:igdtListLine>
        <fr:igdtQuantity>2 Prise(n)</fr:igdtQuantity>
        <fr:igdtName ref="">Pfeffer, schwarzer, frisch aus der Mühle</fr:igdtName>
      </fr:igdtListLine>
      <fr:igdtListLine>
        <fr:igdtQuantity>n. B.</fr:igdtQuantity>
        <fr:igdtName ref="sprossen">Mungobohnenkeimlinge</fr:igdtName>
      </fr:igdtListLine>
      <fr:igdtListLine>
        <fr:igdtQuantity>n. B.</fr:igdtQuantity>
        <fr:igdtName ref="blüten">Blüten und Blätter</fr:igdtName>
      </fr:igdtListLine>
    </fr:igdtList>
  </fr:recipeIngredients>
  <fr:recipeInstructions>
    <fr:instruction>
      <fr:instrStepName/>
      <fr:instrStepText/>
    </fr:instruction>
  </fr:recipeInstructions>
  <fr:recipeSideDish/>
  <fr:recipeOrigin/>
  <fr:recipeSeeAlso/>
  <fr:recipeLicense/>
</fr:recipe>