<?xml version="1.0"?>
<fr:recipe xmlns:fr="http://fruschtique.de/ns/recipe" xmlns:xsi="http://www.w3.org/2001/XMLSchema-instance" xsi:schemaLocation="http://fruschtique.de/ns/recipe file:///c:/Users/nlutt/Documents/Websites/tools/recipe.xsd" rcpID="ck-800031183630518">
  <fr:meta>
    <fr:book>ckCollections</fr:book>
    <fr:chapter>Passionsfrucht</fr:chapter>
  </fr:meta>
  <fr:recipeName>ck-0373-Muschis</fr:recipeName>
  <fr:recipeKeywords/>
  <fr:recipeIntro/>
  <fr:recipeIngredients>
    <fr:igdtList>
      <fr:igdtListName/>
      <fr:igdtListLine>
        <fr:igdtQuantity>200 ml</fr:igdtQuantity>
        <fr:igdtName>Sahne</fr:igdtName>
      </fr:igdtListLine>
      <fr:igdtListLine>
        <fr:igdtQuantity>200 ml</fr:igdtQuantity>
        <fr:igdtName>Wodka</fr:igdtName>
      </fr:igdtListLine>
      <fr:igdtListLine>
        <fr:igdtQuantity>100 g</fr:igdtQuantity>
        <fr:igdtName>Zucker</fr:igdtName>
      </fr:igdtListLine>
      <fr:igdtListLine>
        <fr:igdtQuantity>1 Pck.</fr:igdtQuantity>
        <fr:igdtName>Vanillinzucker</fr:igdtName>
      </fr:igdtListLine>
      <fr:igdtListLine>
        <fr:igdtQuantity>1 Liter</fr:igdtQuantity>
        <fr:igdtName>Maracujasaft</fr:igdtName>
      </fr:igdtListLine>
    </fr:igdtList>
  </fr:recipeIngredients>
  <fr:recipeInstructions>
    <fr:instruction>
      <fr:instrStepName/>
      <fr:instrStepText/>
    </fr:instruction>
  </fr:recipeInstructions>
  <fr:recipeSideDish/>
  <fr:recipeOrigin/>
  <fr:recipeSeeAlso/>
  <fr:recipeLicense/>
</fr:recipe>