<?xml version="1.0" ?><fr:recipe xmlns:fr="http://fruschtique.de/ns/recipe" xmlns:xsi="http://www.w3.org/2001/XMLSchema-instance" xsi:schemaLocation="http://fruschtique.de/ns/recipe file:///c:/Users/nlutt/Documents/Websites/tools/recipe.xsd" rcpID="ck-2326151370636865">
  <fr:meta>
    <fr:book>ckCollections</fr:book>
    <fr:chapter>03 Mangold</fr:chapter>
  </fr:meta>
  <fr:recipeName>Mangold-Reissuppe</fr:recipeName>
  <fr:recipeKeywords/>
  <fr:recipeIntro/>
  <fr:recipeIngredients>
    <fr:igdtList>
      <fr:igdtListName/>
      <fr:igdtListLine>
        <fr:igdtQuantity>25 g</fr:igdtQuantity>
        <fr:igdtName ref="butter">Butter</fr:igdtName>
      </fr:igdtListLine>
      <fr:igdtListLine>
        <fr:igdtQuantity>150 ml</fr:igdtQuantity>
        <fr:igdtName ref="weißwein">Weißwein, trocken</fr:igdtName>
      </fr:igdtListLine>
      <fr:igdtListLine>
        <fr:igdtQuantity>140 g</fr:igdtQuantity>
        <fr:igdtName ref="reis">Basmati</fr:igdtName>
      </fr:igdtListLine>
      <fr:igdtListLine>
        <fr:igdtQuantity>200 g</fr:igdtQuantity>
        <fr:igdtName ref="mangold">Mangold, Blätter</fr:igdtName>
      </fr:igdtListLine>
      <fr:igdtListLine>
        <fr:igdtQuantity>2 Zehe/n</fr:igdtQuantity>
        <fr:igdtName ref="knoblauch">Knoblauch</fr:igdtName>
      </fr:igdtListLine>
      <fr:igdtListLine>
        <fr:igdtQuantity>4 EL</fr:igdtQuantity>
        <fr:igdtName ref="sojasauce">Sojasauce</fr:igdtName>
      </fr:igdtListLine>
      <fr:igdtListLine>
        <fr:igdtQuantity>n. B.</fr:igdtQuantity>
        <fr:igdtName ref="ingwer">Ingwer, frisch</fr:igdtName>
      </fr:igdtListLine>
      <fr:igdtListLine>
        <fr:igdtQuantity>n. B.</fr:igdtQuantity>
        <fr:igdtName ref="chilischote">Chilischote(n), frische</fr:igdtName>
      </fr:igdtListLine>
      <fr:igdtListLine>
        <fr:igdtQuantity>700 ml</fr:igdtQuantity>
        <fr:igdtName ref="brühe">Brühe</fr:igdtName>
      </fr:igdtListLine>
    </fr:igdtList>
  </fr:recipeIngredients>
  <fr:recipeInstructions>
    <fr:instruction>
      <fr:instrStepName/>
      <fr:instrStepText/>
    </fr:instruction>
  </fr:recipeInstructions>
  <fr:recipeSideDish/>
  <fr:recipeOrigin/>
  <fr:recipeSeeAlso/>
  <fr:recipeLicense/>
</fr:recipe>